auth0plus/__init__.py
auth0plus/exceptions.py
auth0plus/oauth.py
auth0plus/settings.py
auth0plus/management/__init__.py
auth0plus/management/auth0p.py
auth0plus/management/base_endpoints.py
auth0plus/management/queryset.py
auth0plus/management/rest.py
auth0plus/management/users.py
auth0plus-0.3.0.dist-info/DESCRIPTION.rst
auth0plus-0.3.0.dist-info/METADATA
auth0plus-0.3.0.dist-info/RECORD
auth0plus-0.3.0.dist-info/WHEEL
auth0plus-0.3.0.dist-info/metadata.json
auth0plus-0.3.0.dist-info/top_level.txt
