Metadata-Version: 2.0
Name: auth0plus
Version: 0.3.0
Summary: Unofficial enhancements to the Auth0-python package
Home-page: https://github.com/bretth/auth0plus
Author: Brett Haydon
Author-email: brett@haydon.id.au
License: ISCL
Keywords: auth0plus
Platform: UNKNOWN
Classifier: Development Status :: 4 - Beta
Classifier: Intended Audience :: Developers
Classifier: License :: OSI Approved :: ISC License (ISCL)
Classifier: Natural Language :: English
Classifier: Programming Language :: Python :: 2
Classifier: Programming Language :: Python :: 2.7
Classifier: Programming Language :: Python :: 3
Classifier: Programming Language :: Python :: 3.4
Classifier: Programming Language :: Python :: 3.5
Classifier: Programming Language :: Python :: 3.6
Requires-Dist: combomethod
Requires-Dist: requests
